test/__init__.py
test/connections_vizportal.py
test/data_connections.py
test/test_get_workbooks.py
vizportal/__init__.py
vizportal/endpoints.py
vizportal/helpers.py
vizportal/pager.py
vizportal/payload.py
vizportal/req_options.py
vizportal/viz_portal_call.py
tableau_vizportal_client-1.0.4.dist-info/METADATA
tableau_vizportal_client-1.0.4.dist-info/WHEEL
tableau_vizportal_client-1.0.4.dist-info/top_level.txt
tableau_vizportal_client-1.0.4.dist-info/RECORD
