Metadata-Version: 2.1
Name: tableau-vizportal-client
Version: 1.0.4
Summary: A helper addon for TableauServerClient to simplify making API calls to the Tableau Vizportal API
Home-page: https://github.com/FsuLauncherComp/tableau-vizportal-client
Author: Rody Zakovich
Author-email: rodyzakovich@gmail.com
Classifier: Programming Language :: Python :: 3
Classifier: License :: OSI Approved :: MIT License
Classifier: Operating System :: OS Independent
Requires-Python: >=3.6
Requires-Dist: tableauserverclient >=0.11
